{"Venues":[{"yelp url":"http:\/\/www.yelp.com\/biz\/tamarack-the-best-of-west-virginia-beckley","name":"Tamarack: The Best of West Virginia","Lat":37.8164,"long":-81.2329,"url":"http:\/\/www.tamarackwv.com"},{"yelp url":"http:\/\/www.yelp.com\/biz\/starbucks-beckley","name":"Starbucks","Lat":37.8164,"long":-81.2329,"url":"http:\/\/www.starbucks.com"},{"yelp url":"http:\/\/www.yelp.com\/biz\/char-beckley","name":"Char","Lat":37.8164,"long":-81.2329,"url":"http:\/\/www.the-char.com%2F"},{"yelp url":"http:\/\/www.yelp.com\/biz\/pasquale-mira-spaghetti-house-beckley","name":"Pasquale Mira Spaghetti House","Lat":37.8164,"long":-81.2329,"url":null},{"yelp url":"http:\/\/www.yelp.com\/biz\/mickeys-beckley","name":"Mickey's","Lat":37.8164,"long":-81.2329,"url":null},{"yelp url":"http:\/\/www.yelp.com\/biz\/hampton-inn-beckley-beckley","name":"Hampton Inn Beckley","Lat":37.8164,"long":-81.2329,"url":"http:\/\/hamptoninn1.hilton.com"},{"yelp url":"http:\/\/www.yelp.com\/biz\/young-chows-chinese-cuisine-beckley","name":"Young Chow's Chinese Cuisine","Lat":37.8164,"long":-81.2329,"url":null},{"yelp url":"http:\/\/www.yelp.com\/biz\/beckley-travel-plaza-beckley","name":"Beckley Travel Plaza","Lat":37.8164,"long":-81.2329,"url":"http:\/\/www.transportation.wv.gov%2Fturnpike%2FPages%2FBeckleyTravelPlaza.aspx"},{"yelp url":"http:\/\/www.yelp.com\/biz\/holiday-inn-hotel-and-suites-beckley-beckley","name":"Holiday Inn Hotel & Suites Beckley","Lat":37.8164,"long":-81.2329,"url":"http:\/\/www.holidayinn.com%2Fhotels%2Fus%2Fen%2Fbeckley%2Fbkwhr%2Fhoteldetail"},{"yelp url":"http:\/\/www.yelp.com\/biz\/go-mart-inc-beckley-2","name":"Go-Mart Inc","Lat":37.8164,"long":-81.2329,"url":null},{"yelp url":"http:\/\/www.yelp.com\/biz\/bob-evans-restaurant-beckley","name":"Bob Evans Restaurant","Lat":37.8164,"long":-81.2329,"url":"http:\/\/www.bobevans.com"},{"yelp url":"http:\/\/www.yelp.com\/biz\/courtyard-by-marriott-beckley","name":"Courtyard by Marriott","Lat":37.8164,"long":-81.2329,"url":null},{"yelp url":"http:\/\/www.yelp.com\/biz\/campestre-mexican-restaurant-beckley","name":"Campestre Mexican Restaurant","Lat":37.8164,"long":-81.2329,"url":null},{"yelp url":"http:\/\/www.yelp.com\/biz\/briar-patch-beckley","name":"Briar Patch","Lat":37.8164,"long":-81.2329,"url":null},{"yelp url":"http:\/\/www.yelp.com\/biz\/country-inn-and-suites-by-carlson-beckley-beckley","name":"Country Inn & Suites by Carlson-Beckley","Lat":37.8164,"long":-81.2329,"url":"http:\/\/www.countryinns.com%2Fbeckley-hotel-wv-25801%2Fwvbeck"},{"yelp url":"http:\/\/www.yelp.com\/biz\/outback-steakhouse-beckley","name":"Outback Steakhouse","Lat":37.8164,"long":-81.2329,"url":"http:\/\/www.outback.com%2Fstore.aspx%3Fstore%3D4961%26utm_source%3DGoo%26utm_medium%3Dmaplistings%26utm_campaign%3Dlocalmaps"},{"yelp url":"http:\/\/www.yelp.com\/biz\/quality-inn-beckley","name":"Quality Inn","Lat":37.8164,"long":-81.2329,"url":null},{"yelp url":"http:\/\/www.yelp.com\/biz\/econo-lodge-beckley","name":"Econo Lodge","Lat":37.8164,"long":-81.2329,"url":"http:\/\/www.econolodge.com%2Fhotel%2FWV400"},{"yelp url":"http:\/\/www.yelp.com\/biz\/fujiyama-japanese-steakhouse-beckley","name":"Fujiyama Japanese Steakhouse","Lat":37.8164,"long":-81.2329,"url":"http:\/\/www.fujiyamabeckley.com%2F"},{"yelp url":"http:\/\/www.yelp.com\/biz\/comfort-inn-beckley","name":"Comfort Inn","Lat":37.8164,"long":-81.2329,"url":"http:\/\/www.comfortinn.com%2Fhotel%2Fwv094"},{"yelp url":"http:\/\/www.yelp.com\/biz\/lost-parrot-beach-bar-and-grill-beckley","name":"Lost Parrot Beach Bar & Grill","Lat":37.7782,"long":-81.1882,"url":null},{"yelp url":"http:\/\/www.yelp.com\/biz\/webbs-of-beckley-florist-beckley","name":"Webb's of Beckley Florist","Lat":37.7782,"long":-81.1882,"url":null},{"yelp url":"http:\/\/www.yelp.com\/biz\/mcbees-irish-pub-and-restaurant-beckley","name":"McBees Irish Pub and Restaurant","Lat":37.7782,"long":-81.1882,"url":null},{"yelp url":"http:\/\/www.yelp.com\/biz\/the-bake-shoppe-beckley","name":"The Bake Shoppe","Lat":37.7782,"long":-81.1882,"url":null},{"yelp url":"http:\/\/www.yelp.com\/biz\/cucumber-and-company-beckley-2","name":"Cucumber & Company","Lat":37.7782,"long":-81.1882,"url":"http:\/\/www.cucumberandcompany.com"},{"yelp url":"http:\/\/www.yelp.com\/biz\/cucumber-and-company-beckley","name":"Cucumber & Company","Lat":37.7782,"long":-81.1882,"url":"http:\/\/www.cucumberandcompany.com"},{"yelp url":"http:\/\/www.yelp.com\/biz\/taste-of-india-beckley","name":"Taste Of India","Lat":37.7782,"long":-81.1882,"url":null},{"yelp url":"http:\/\/www.yelp.com\/biz\/smokin-guns-tattoo-beckley","name":"Smokin' Guns Tattoo","Lat":37.7782,"long":-81.1882,"url":"http:\/\/www.sgtattoo.com"},{"yelp url":"http:\/\/www.yelp.com\/biz\/aangan-indian-cuisine-beckley","name":"Aangan Indian Cuisine","Lat":37.7782,"long":-81.1882,"url":null},{"yelp url":"http:\/\/www.yelp.com\/biz\/quiznos-sub-beckley","name":"Quiznos Sub","Lat":37.7782,"long":-81.1882,"url":"http:\/\/www.quiznos.com"},{"yelp url":"http:\/\/www.yelp.com\/biz\/king-tut-drive-in-beckley","name":"King Tut Drive-In","Lat":37.7782,"long":-81.1882,"url":"http:\/\/www.kingtutdrivein.com%2F"},{"yelp url":"http:\/\/www.yelp.com\/biz\/brightwell-photography-beckley","name":"Brightwell Photography","Lat":37.7782,"long":-81.1882,"url":"http:\/\/brightwellphotography.com"},{"yelp url":"http:\/\/www.yelp.com\/biz\/dobra-zupas-beckley","name":"Dobra Zupa's","Lat":37.7782,"long":-81.1882,"url":null},{"yelp url":"http:\/\/www.yelp.com\/biz\/exhibition-coal-mine-beckley","name":"Exhibition Coal Mine","Lat":37.7782,"long":-81.1882,"url":"http:\/\/www.beckley.org"},{"yelp url":"http:\/\/www.yelp.com\/biz\/padrinos-italian-restaurant-beckley","name":"Padrinos Italian Restaurant","Lat":37.7782,"long":-81.1882,"url":null},{"yelp url":"http:\/\/www.yelp.com\/biz\/calacinos-pizzeria-beckley","name":"Calacino's Pizzeria","Lat":37.7782,"long":-81.1882,"url":"http:\/\/www.calacinos.com%2F"},{"yelp url":"http:\/\/www.yelp.com\/biz\/anne-stover-dba-mama-annes-beckley","name":"Anne Stover Dba Mama Anne's","Lat":37.7782,"long":-81.1882,"url":null},{"yelp url":"http:\/\/www.yelp.com\/biz\/jonesn-for-a-good-burger-beckley","name":"Jonesn For A Good Burger","Lat":37.7782,"long":-81.1882,"url":null},{"yelp url":"http:\/\/www.yelp.com\/biz\/southern-reds-barbeque-beckley","name":"Southern Red's Barbeque","Lat":37.7782,"long":-81.1882,"url":null},{"yelp url":"http:\/\/www.yelp.com\/biz\/campestre-mexican-restaurant-beckley","name":"Campestre Mexican Restaurant","Lat":37.7782,"long":-81.1882,"url":null},{"yelp url":"http:\/\/www.yelp.com\/biz\/lost-parrot-beach-bar-and-grill-beckley","name":"Lost Parrot Beach Bar & Grill","Lat":37.7782,"long":-81.1882,"url":null},{"yelp url":"http:\/\/www.yelp.com\/biz\/webbs-of-beckley-florist-beckley","name":"Webb's of Beckley Florist","Lat":37.7782,"long":-81.1882,"url":null},{"yelp url":"http:\/\/www.yelp.com\/biz\/mcbees-irish-pub-and-restaurant-beckley","name":"McBees Irish Pub and Restaurant","Lat":37.7782,"long":-81.1882,"url":null},{"yelp url":"http:\/\/www.yelp.com\/biz\/the-bake-shoppe-beckley","name":"The Bake Shoppe","Lat":37.7782,"long":-81.1882,"url":null},{"yelp url":"http:\/\/www.yelp.com\/biz\/cucumber-and-company-beckley-2","name":"Cucumber & Company","Lat":37.7782,"long":-81.1882,"url":"http:\/\/www.cucumberandcompany.com"},{"yelp url":"http:\/\/www.yelp.com\/biz\/cucumber-and-company-beckley","name":"Cucumber & Company","Lat":37.7782,"long":-81.1882,"url":"http:\/\/www.cucumberandcompany.com"},{"yelp url":"http:\/\/www.yelp.com\/biz\/taste-of-india-beckley","name":"Taste Of India","Lat":37.7782,"long":-81.1882,"url":null},{"yelp url":"http:\/\/www.yelp.com\/biz\/smokin-guns-tattoo-beckley","name":"Smokin' Guns Tattoo","Lat":37.7782,"long":-81.1882,"url":"http:\/\/www.sgtattoo.com"},{"yelp url":"http:\/\/www.yelp.com\/biz\/aangan-indian-cuisine-beckley","name":"Aangan Indian Cuisine","Lat":37.7782,"long":-81.1882,"url":null},{"yelp url":"http:\/\/www.yelp.com\/biz\/quiznos-sub-beckley","name":"Quiznos Sub","Lat":37.7782,"long":-81.1882,"url":"http:\/\/www.quiznos.com"},{"yelp url":"http:\/\/www.yelp.com\/biz\/king-tut-drive-in-beckley","name":"King Tut Drive-In","Lat":37.7782,"long":-81.1882,"url":"http:\/\/www.kingtutdrivein.com%2F"},{"yelp url":"http:\/\/www.yelp.com\/biz\/brightwell-photography-beckley","name":"Brightwell Photography","Lat":37.7782,"long":-81.1882,"url":"http:\/\/brightwellphotography.com"},{"yelp url":"http:\/\/www.yelp.com\/biz\/dobra-zupas-beckley","name":"Dobra Zupa's","Lat":37.7782,"long":-81.1882,"url":null},{"yelp url":"http:\/\/www.yelp.com\/biz\/exhibition-coal-mine-beckley","name":"Exhibition Coal Mine","Lat":37.7782,"long":-81.1882,"url":"http:\/\/www.beckley.org"},{"yelp url":"http:\/\/www.yelp.com\/biz\/padrinos-italian-restaurant-beckley","name":"Padrinos Italian Restaurant","Lat":37.7782,"long":-81.1882,"url":null},{"yelp url":"http:\/\/www.yelp.com\/biz\/calacinos-pizzeria-beckley","name":"Calacino's Pizzeria","Lat":37.7782,"long":-81.1882,"url":"http:\/\/www.calacinos.com%2F"},{"yelp url":"http:\/\/www.yelp.com\/biz\/anne-stover-dba-mama-annes-beckley","name":"Anne Stover Dba Mama Anne's","Lat":37.7782,"long":-81.1882,"url":null},{"yelp url":"http:\/\/www.yelp.com\/biz\/jonesn-for-a-good-burger-beckley","name":"Jonesn For A Good Burger","Lat":37.7782,"long":-81.1882,"url":null},{"yelp url":"http:\/\/www.yelp.com\/biz\/southern-reds-barbeque-beckley","name":"Southern Red's Barbeque","Lat":37.7782,"long":-81.1882,"url":null},{"yelp url":"http:\/\/www.yelp.com\/biz\/campestre-mexican-restaurant-beckley","name":"Campestre Mexican Restaurant","Lat":37.7782,"long":-81.1882,"url":null}],"City":"Beckley"}